DMBotTools/__init__.py
DMBotTools/color.py
DMBotTools/coordinate.py
DMBotTools/misc.py
DMBotTools/shape.py
DMBotTools-0.0.2.dist-info/LICENSE.md
DMBotTools-0.0.2.dist-info/METADATA
DMBotTools-0.0.2.dist-info/WHEEL
DMBotTools-0.0.2.dist-info/top_level.txt
DMBotTools-0.0.2.dist-info/RECORD
