Metadata-Version: 2.1
Name: DMBotTools
Version: 0.0.2
Summary: Инструменты используемые для проектов DMBot
Home-page: https://github.com/AngelsAndDemonsDM/DM-Bot-tools
Author: Angels And Demons dev team
Author-email: dm.bot.adm@gmail.com
License: GPL-3.0
Classifier: Programming Language :: Python :: 3
Classifier: License :: OSI Approved :: GNU General Public License v3 (GPLv3)
Classifier: Operating System :: OS Independent
Requires-Python: >=3.11
License-File: LICENSE.md
